pyurlon/__about__.py
pyurlon/__init__.py
pyurlon/urlon.py
pyurlon-0.2.0.dist-info/METADATA
pyurlon-0.2.0.dist-info/WHEEL
pyurlon-0.2.0.dist-info/licenses/LICENSE.txt
pyurlon-0.2.0.dist-info/RECORD
