Metadata-Version: 2.3
Name: pyurlon
Version: 0.2.0
Summary: Python port of https://github.com/cerebral/urlon javascript package
Project-URL: Documentation, https://github.com/unknown/pyurlon#readme
Project-URL: Issues, https://github.com/unknown/pyurlon/issues
Project-URL: Source, https://github.com/unknown/pyurlon
Author-email: adamws <adamws@users.noreply.github.com>
License-Expression: MIT
License-File: LICENSE.txt
Classifier: Development Status :: 4 - Beta
Classifier: Intended Audience :: Developers
Classifier: License :: OSI Approved :: MIT License
Classifier: Programming Language :: Python
Classifier: Programming Language :: Python :: 3.7
Classifier: Programming Language :: Python :: 3.8
Classifier: Programming Language :: Python :: 3.9
Classifier: Programming Language :: Python :: 3.10
Classifier: Programming Language :: Python :: 3.11
Classifier: Programming Language :: Python :: 3.12
Classifier: Programming Language :: Python :: 3.13
Classifier: Programming Language :: Python :: Implementation :: CPython
Classifier: Programming Language :: Python :: Implementation :: PyPy
Classifier: Topic :: Internet
Classifier: Topic :: Software Development :: Libraries
Requires-Python: >=3.7
